vcf_pg_loader/__init__.py
vcf_pg_loader/annotation_config.py
vcf_pg_loader/annotation_loader.py
vcf_pg_loader/annotation_schema.py
vcf_pg_loader/annotator.py
vcf_pg_loader/benchmark.py
vcf_pg_loader/cli.py
vcf_pg_loader/columns.py
vcf_pg_loader/config.py
vcf_pg_loader/db_loader.py
vcf_pg_loader/doctor.py
vcf_pg_loader/expression.py
vcf_pg_loader/loader.py
vcf_pg_loader/managed_db.py
vcf_pg_loader/models.py
vcf_pg_loader/normalizer.py
vcf_pg_loader/retry.py
vcf_pg_loader/schema.py
vcf_pg_loader/type_mapping.py
vcf_pg_loader/vcf_parser.py
vcf_pg_loader-0.5.4.dist-info/METADATA
vcf_pg_loader-0.5.4.dist-info/WHEEL
vcf_pg_loader-0.5.4.dist-info/entry_points.txt
vcf_pg_loader-0.5.4.dist-info/licenses/LICENSE
vcf_pg_loader-0.5.4.dist-info/RECORD
