Metadata-Version: 2.4
Name: vcf-pg-loader
Version: 0.5.4
Summary: High-performance VCF to PostgreSQL loader with clinical-grade compliance
Project-URL: Homepage, https://github.com/Zacharyr41/vcf-pg-loader
Project-URL: Documentation, https://github.com/Zacharyr41/vcf-pg-loader/tree/main/docs
Project-URL: Repository, https://github.com/Zacharyr41/vcf-pg-loader
Project-URL: Issues, https://github.com/Zacharyr41/vcf-pg-loader/issues
Author-email: Zachary Rothstein <zacharyr41@gmail.com>
License: MIT
License-File: LICENSE
Keywords: bioinformatics,genomics,postgresql,variants,vcf
Classifier: Development Status :: 4 - Beta
Classifier: Environment :: Console
Classifier: Intended Audience :: Science/Research
Classifier: License :: OSI Approved :: MIT License
Classifier: Operating System :: MacOS
Classifier: Operating System :: POSIX :: Linux
Classifier: Programming Language :: Python :: 3
Classifier: Programming Language :: Python :: 3.9
Classifier: Programming Language :: Python :: 3.10
Classifier: Programming Language :: Python :: 3.11
Classifier: Programming Language :: Python :: 3.12
Classifier: Topic :: Scientific/Engineering :: Bio-Informatics
Requires-Python: >=3.9
Requires-Dist: anyio>=4.3.0
Requires-Dist: asyncpg>=0.29.0
Requires-Dist: cyvcf2>=0.31.0
Requires-Dist: docker>=7.0.0
Requires-Dist: pydantic>=2.6.0
Requires-Dist: rich>=13.7.0
Requires-Dist: typer>=0.12.0
Provides-Extra: dev
Requires-Dist: bump-my-version>=0.24.0; extra == 'dev'
Requires-Dist: factory-boy>=3.3.0; extra == 'dev'
Requires-Dist: hypothesis>=6.98.0; extra == 'dev'
Requires-Dist: mypy>=1.8.0; extra == 'dev'
Requires-Dist: pre-commit>=3.6.0; extra == 'dev'
Requires-Dist: pytest-asyncio>=0.23.0; extra == 'dev'
Requires-Dist: pytest-cov>=4.1.0; extra == 'dev'
Requires-Dist: pytest-xdist>=3.5.0; extra == 'dev'
Requires-Dist: pytest>=8.0.0; extra == 'dev'
Requires-Dist: ruff>=0.3.0; extra == 'dev'
Requires-Dist: testcontainers[postgres]>=4.0.0; extra == 'dev'
